colourise_output/__init__.py
colourise_output/__main__.py
colourise_output/colourise_output.py
tests/__init__.py
tests/test_colourise_output.py
colourise_output-1.1.6.dist-info/LICENSE
colourise_output-1.1.6.dist-info/METADATA
colourise_output-1.1.6.dist-info/WHEEL
colourise_output-1.1.6.dist-info/top_level.txt
colourise_output-1.1.6.dist-info/RECORD
