Metadata-Version: 2.1
Name: colourise_output
Version: 1.1.6
Summary: A module to help add colour in the terminal using batch colour codes.
Home-page: https://github.com/Hanra-s-work/colourise_output
Author: Henry Letellier
Author-email: henrysoftwarehouse@protonmail.com
Classifier: Programming Language :: Python :: 3
Classifier: License :: OSI Approved :: MIT License
Classifier: Operating System :: OS Independent
License-File: LICENSE
Requires-Dist: colorama==0.4.6
